pypatterns/__init__.py
pypatterns/alphabet_patterns/__init__.py
pypatterns/get_pattern_code/__init__.py
pypatterns/name/__init__.py
pypatterns/name/name.py
pypatterns/name_patterns/__init__.py
pypatterns/number_patterns/__init__.py
pypatterns/star_patterns/__init__.py
pypatterns_575-2.1.2.dist-info/LICENSE
pypatterns_575-2.1.2.dist-info/METADATA
pypatterns_575-2.1.2.dist-info/WHEEL
pypatterns_575-2.1.2.dist-info/top_level.txt
pypatterns_575-2.1.2.dist-info/RECORD
